_tanway/__init__.py
_tanway/_tanway.cp39-win_amd64.pyd
_tanway/algo.dll
_tanway/lidar.dll
tanway/__init__.py
tanway/_version.py
tanway/device_info.py
tanway/lidar.py
tanway/point_cloud.py
tanway-3.0.12.2.0.4.dist-info/METADATA
tanway-3.0.12.2.0.4.dist-info/WHEEL
tanway-3.0.12.2.0.4.dist-info/top_level.txt
tanway-3.0.12.2.0.4.dist-info/RECORD
